{
    "stat": "ok", 
    "object": {
        "gallery_text": null, 
        "year_start": null, 
        "videos": null, 
        "type_id": "35238163", 
        "medium": "screenprint on paper", 
        "tms:id": "177538", 
        "images": [
            {
                "sq": {
                    "url": "https://images.collection.cooperhewitt.org/90305_cdd3465655c91beb_sq.jpg", 
                    "width": 300, 
                    "height": 300, 
                    "is_primary": "1", 
                    "image_id": "90305"
                }, 
                "b": {
                    "url": "https://images.collection.cooperhewitt.org/90305_cdd3465655c91beb_b.jpg", 
                    "width": 729, 
                    "height": 1024, 
                    "is_primary": "1", 
                    "image_id": "90305"
                }, 
                "d": {
                    "url": "https://images.collection.cooperhewitt.org/90305_cdd3465655c91beb_d.gif", 
                    "width": 228, 
                    "height": 320, 
                    "is_primary": "1", 
                    "image_id": "90305"
                }, 
                "z": {
                    "url": "https://images.collection.cooperhewitt.org/90305_cdd3465655c91beb_z.jpg", 
                    "width": 456, 
                    "height": 640, 
                    "is_primary": "1", 
                    "image_id": "90305"
                }, 
                "n": {
                    "url": "https://images.collection.cooperhewitt.org/90305_cdd3465655c91beb_n.jpg", 
                    "width": 228, 
                    "height": 320, 
                    "is_primary": "1", 
                    "image_id": "90305"
                }
            }, 
            {
                "sq": {
                    "url": "https://images.collection.cooperhewitt.org/206423_54ed5027b7f69e31_sq.jpg", 
                    "width": 300, 
                    "height": 300, 
                    "is_primary": "0", 
                    "image_id": "206423"
                }, 
                "b": {
                    "url": "https://images.collection.cooperhewitt.org/206423_54ed5027b7f69e31_b.jpg", 
                    "width": 744, 
                    "height": 1024, 
                    "is_primary": "0", 
                    "image_id": "206423"
                }, 
                "d": {
                    "url": "https://images.collection.cooperhewitt.org/206423_54ed5027b7f69e31_d.gif", 
                    "width": 233, 
                    "height": 320, 
                    "is_primary": "0", 
                    "image_id": "206423"
                }, 
                "z": {
                    "url": "https://images.collection.cooperhewitt.org/206423_54ed5027b7f69e31_z.jpg", 
                    "width": 465, 
                    "height": 640, 
                    "is_primary": "0", 
                    "image_id": "206423"
                }, 
                "n": {
                    "url": "https://images.collection.cooperhewitt.org/206423_54ed5027b7f69e31_n.jpg", 
                    "width": 233, 
                    "height": 320, 
                    "is_primary": "0", 
                    "image_id": "206423"
                }
            }
        ], 
        "id": "18618009", 
        "has_no_known_copyright": null, 
        "woe:country_name": "United States", 
        "dimensions": "53.2 x 38 cm (20 15/16 x 14 15/16 in.)", 
        "title": "Poster, IBM / Unravel", 
        "provenance": "1981: acquired by Museum", 
        "participants": [
            {
                "person_name": "IBM", 
                "role_url": "https://collection.cooperhewitt.org/roles/35236667/", 
                "role_id": "35236667", 
                "role_name": "Client", 
                "person_date": "USA", 
                "role_display_name": "Client:", 
                "person_id": "18041871", 
                "person_url": "https://collection.cooperhewitt.org/people/18041871/"
            }, 
            {
                "person_name": "Ken White", 
                "role_url": "https://collection.cooperhewitt.org/roles/35236655/", 
                "role_id": "35236655", 
                "role_name": "Designer", 
                "person_date": "American, 1935-1985", 
                "role_display_name": "Designed by", 
                "person_id": "18042357", 
                "person_url": "https://collection.cooperhewitt.org/people/18042357/"
            }
        ], 
        "decade": null, 
        "label_text": null, 
        "woe:country": "23424977", 
        "dimensions_raw": {
            "width": [
                "38.00", 
                "centimeters"
            ], 
            "height": [
                "53.20", 
                "centimeters"
            ]
        }, 
        "department_id": "35347493", 
        "title_raw": "IBM / Unravel", 
        "justification": null, 
        "media_id": "35431679", 
        "description": "On gray ground a black ball of raveled string. In white text, upper left: Unravel; upper right: IBM [logo] Suggest!", 
        "creditline": "Gift of Various Donors", 
        "on_display": null, 
        "markings": null, 
        "is_loan_object": 0, 
        "date": null, 
        "url": "https://collection.cooperhewitt.org/objects/18618009/", 
        "type": "poster", 
        "accession_number": "1981-29-437", 
        "year_end": null, 
        "signed": null, 
        "inscribed": null, 
        "period_id": null, 
        "year_acquired": "1981", 
        "woe:country_id": "23424977"
    }
}