{
    "stat": "ok", 
    "object": {
        "gallery_text": "To promote an exhibition on the design of coffee pots, Schmauder, in her first award-winning poster,   employs a variety of patterns to suggest the appearance of such an object through a collage of floral and gingham patterns. Although the layering of images suggests a manual cut-and-paste technique (as is customary with the traditional process of collage) it is likely Schmauder used software to create the desired visual effect. Image manipulation software allows designers greater freedom for experimentation because ideas can be realized (and changed) more quickly.", 
        "year_start": 1996, 
        "videos": null, 
        "type_id": "35238163", 
        "medium": "screenprint on wove paper", 
        "tms:id": "255461", 
        "images": [
            {
                "sq": {
                    "url": "https://images.collection.cooperhewitt.org/46826_9092dcc2996beb22_sq.jpg", 
                    "width": 300, 
                    "height": 300, 
                    "is_primary": "1", 
                    "image_id": "46826"
                }, 
                "b": {
                    "url": "https://images.collection.cooperhewitt.org/46826_9092dcc2996beb22_b.jpg", 
                    "width": 719, 
                    "height": 1024, 
                    "is_primary": "1", 
                    "image_id": "46826"
                }, 
                "d": {
                    "url": "https://images.collection.cooperhewitt.org/46826_9092dcc2996beb22_d.gif", 
                    "width": 225, 
                    "height": 320, 
                    "is_primary": "1", 
                    "image_id": "46826"
                }, 
                "z": {
                    "url": "https://images.collection.cooperhewitt.org/46826_9092dcc2996beb22_z.jpg", 
                    "width": 449, 
                    "height": 640, 
                    "is_primary": "1", 
                    "image_id": "46826"
                }, 
                "n": {
                    "url": "https://images.collection.cooperhewitt.org/46826_9092dcc2996beb22_n.jpg", 
                    "width": 225, 
                    "height": 320, 
                    "is_primary": "1", 
                    "image_id": "46826"
                }
            }
        ], 
        "id": "18758351", 
        "has_no_known_copyright": null, 
        "woe:country_name": "Switzerland", 
        "dimensions": "128 x 90.5 cm (50 3/8 x 35 5/8 in.)", 
        "title": "Poster, Silber Reflexe:  Kaffekanne und Design, 1996", 
        "provenance": "Sara and Marc Benda (acquired new and directly from designer, Claudia Schmauder); 2010: acquired by Museum", 
        "participants": [
            {
                "person_name": "Johann Jacobs Museum", 
                "role_url": "https://collection.cooperhewitt.org/roles/35236667/", 
                "role_id": "35236667", 
                "role_name": "Client", 
                "person_date": "Zürich, Switzerland, founded 1984", 
                "role_display_name": "Client:", 
                "person_id": "18063579", 
                "person_url": "https://collection.cooperhewitt.org/people/18063579/"
            }, 
            {
                "person_name": "Marc Benda", 
                "role_url": "https://collection.cooperhewitt.org/roles/35351535/", 
                "role_id": "35351535", 
                "role_name": "Donor", 
                "person_date": "", 
                "role_display_name": "Donated by", 
                "person_id": "18062523", 
                "person_url": "https://collection.cooperhewitt.org/people/18062523/"
            }, 
            {
                "person_name": "Sara Benda", 
                "role_url": "https://collection.cooperhewitt.org/roles/35351535/", 
                "role_id": "35351535", 
                "role_name": "Donor", 
                "person_date": "", 
                "role_display_name": "Donated by", 
                "person_id": "18063205", 
                "person_url": "https://collection.cooperhewitt.org/people/18063205/"
            }, 
            {
                "person_name": "Claudia Schmauder", 
                "role_url": "https://collection.cooperhewitt.org/roles/35236655/", 
                "role_id": "35236655", 
                "role_name": "Designer", 
                "person_date": "Swiss, born 1969", 
                "role_display_name": "Designed by", 
                "person_id": "68738763", 
                "person_url": "https://collection.cooperhewitt.org/people/68738763/"
            }
        ], 
        "decade": "1990", 
        "label_text": null, 
        "woe:country": "23424957", 
        "dimensions_raw": {
            "width": [
                "90.50", 
                "centimeters"
            ], 
            "height": [
                "128.00", 
                "centimeters"
            ]
        }, 
        "department_id": "35347493", 
        "title_raw": "Silber Reflexe:  Kaffekanne und Design", 
        "justification": null, 
        "media_id": "35399029", 
        "description": "On a gray and light peach floral background, there is a silver and gingham water pitcher; in gray block text, across lower margin: SILBER / REFLEXE; overlaid, in black and red: 24.11.1996-26.10-1997 / Johann Jacobs Museum / Sammlung zur Kulturgeschichte des Kaffees / Kaffeekanne und Design – Eine Entdeckungsreise.", 
        "creditline": "Gift of Sara and Marc Benda", 
        "on_display": null, 
        "markings": null, 
        "is_loan_object": 0, 
        "date": "1996", 
        "url": "https://collection.cooperhewitt.org/objects/18758351/", 
        "type": "poster", 
        "accession_number": "2010-21-72", 
        "year_end": 1996, 
        "signed": null, 
        "inscribed": "Printed in black ink, lower right edge: Claudia Schmauder. Hohere Schule fur Gestaltung Zurich", 
        "period_id": null, 
        "year_acquired": "2010", 
        "woe:country_id": "23424957"
    }
}