{
    "stat": "ok", 
    "object": {
        "gallery_text": null, 
        "year_start": 2000, 
        "videos": null, 
        "type_id": "35238163", 
        "medium": "offset lithograph on silver mylar", 
        "tms:id": "255415", 
        "images": [
            {
                "sq": {
                    "url": "https://images.collection.cooperhewitt.org/46897_90f0ac475545f63b_sq.jpg", 
                    "width": 300, 
                    "height": 300, 
                    "is_primary": "1", 
                    "image_id": "46897"
                }, 
                "b": {
                    "url": "https://images.collection.cooperhewitt.org/46897_90f0ac475545f63b_b.jpg", 
                    "width": 690, 
                    "height": 1024, 
                    "is_primary": "1", 
                    "image_id": "46897"
                }, 
                "d": {
                    "url": "https://images.collection.cooperhewitt.org/46897_90f0ac475545f63b_d.gif", 
                    "width": 216, 
                    "height": 320, 
                    "is_primary": "1", 
                    "image_id": "46897"
                }, 
                "z": {
                    "url": "https://images.collection.cooperhewitt.org/46897_90f0ac475545f63b_z.jpg", 
                    "width": 431, 
                    "height": 640, 
                    "is_primary": "1", 
                    "image_id": "46897"
                }, 
                "n": {
                    "url": "https://images.collection.cooperhewitt.org/46897_90f0ac475545f63b_n.jpg", 
                    "width": 216, 
                    "height": 320, 
                    "is_primary": "1", 
                    "image_id": "46897"
                }
            }, 
            {
                "sq": {
                    "url": "https://images.collection.cooperhewitt.org/253076_d5e22d197ae81bd1_sq.jpg", 
                    "width": 300, 
                    "height": 300, 
                    "is_primary": "0", 
                    "image_id": "253076"
                }, 
                "b": {
                    "url": "https://images.collection.cooperhewitt.org/253076_d5e22d197ae81bd1_b.jpg", 
                    "width": 699, 
                    "height": 1024, 
                    "is_primary": "0", 
                    "image_id": "253076"
                }, 
                "d": {
                    "url": "https://images.collection.cooperhewitt.org/253076_d5e22d197ae81bd1_d.gif", 
                    "width": 218, 
                    "height": 320, 
                    "is_primary": "0", 
                    "image_id": "253076"
                }, 
                "z": {
                    "url": "https://images.collection.cooperhewitt.org/253076_d5e22d197ae81bd1_z.jpg", 
                    "width": 437, 
                    "height": 640, 
                    "is_primary": "0", 
                    "image_id": "253076"
                }, 
                "n": {
                    "url": "https://images.collection.cooperhewitt.org/253076_d5e22d197ae81bd1_n.jpg", 
                    "width": 218, 
                    "height": 320, 
                    "is_primary": "0", 
                    "image_id": "253076"
                }
            }
        ], 
        "id": "18758261", 
        "has_no_known_copyright": null, 
        "dimensions": "101 x 68 cm (39 3/4 x 26 3/4 in.)", 
        "title": "Poster, Charlie's Angels, 2000", 
        "provenance": "Acquired from dealers, galleries and auction houses by Marc Benda.  Remained with Benda until 2010, when gifted to CHNDM.", 
        "participants": [
            {
                "person_name": "Vox & Associates", 
                "role_url": "https://collection.cooperhewitt.org/roles/35236655/", 
                "role_id": "35236655", 
                "role_name": "Designer", 
                "person_date": "American", 
                "role_display_name": "Designed by", 
                "person_id": "18063507", 
                "person_url": "https://collection.cooperhewitt.org/people/18063507/"
            }, 
            {
                "person_name": "Marc Benda", 
                "role_url": "https://collection.cooperhewitt.org/roles/35351535/", 
                "role_id": "35351535", 
                "role_name": "Donor", 
                "person_date": "", 
                "role_display_name": "Donated by", 
                "person_id": "18062523", 
                "person_url": "https://collection.cooperhewitt.org/people/18062523/"
            }, 
            {
                "person_name": "Sara Benda", 
                "role_url": "https://collection.cooperhewitt.org/roles/35351535/", 
                "role_id": "35351535", 
                "role_name": "Donor", 
                "person_date": "", 
                "role_display_name": "Donated by", 
                "person_id": "18063205", 
                "person_url": "https://collection.cooperhewitt.org/people/18063205/"
            }
        ], 
        "decade": "2000", 
        "label_text": null, 
        "woe:country": null, 
        "dimensions_raw": {
            "width": [
                "68.00", 
                "centimeters"
            ], 
            "height": [
                "101.00", 
                "centimeters"
            ]
        }, 
        "department_id": "35347493", 
        "title_raw": "Charlie's Angels", 
        "justification": null, 
        "media_id": "35434609", 
        "description": "Background: metallic gold, layered with a smaller rectangle in magenta, layered again with a page-size \"A\", covered with yellow and orange flames. At center of image, the photograph of three women posing confrontationally.\nInscriptions: lower center, \"CHARLIE'S / ANGELS\" in orange and yellow, succeded by \"GET SOME ACTION\" in green, and \"COMING SOON\" in gold.", 
        "creditline": "Gift of Sara and Marc Benda", 
        "on_display": null, 
        "markings": null, 
        "is_loan_object": 0, 
        "date": "2000", 
        "url": "https://collection.cooperhewitt.org/objects/18758261/", 
        "type": "poster", 
        "accession_number": "2010-21-29", 
        "year_end": 2000, 
        "signed": null, 
        "inscribed": null, 
        "period_id": null, 
        "year_acquired": "2010", 
        "woe:country_id": null
    }
}